dragonfruit/__init__.py
dragonfruit/_version.txt
dragonfruit/ase_utils.py
dragonfruit/defaults.py
dragonfruit/environments.py
dragonfruit/mincepy.py
dragonfruit/pyos_utils.py
dragonfruit/settings.py
dragonfruit/tools.py
dragonfruit/utils.py
dragonfruit/version.py
dragonfruit/alloys/__init__.py
dragonfruit/alloys/vegard.py
dragonfruit/clease/__init__.py
dragonfruit/clease/paths.py
dragonfruit/clease/pyos.py
dragonfruit/clease/utils.py
dragonfruit/clease/scripts/__init__.py
dragonfruit/clease/scripts/simple_vasp.py
dragonfruit/cli/__init__.py
dragonfruit/cli/db.py
dragonfruit/cli/main.py
dragonfruit/cli/profile_config.py
dragonfruit/cli/sbatch.py
dragonfruit/ionic_liquids/__init__.py
dragonfruit/ionic_liquids/adf_scripts.py
dragonfruit/ionic_liquids/adf_task_scripts.py
dragonfruit/ionic_liquids/constants.py
dragonfruit/ionic_liquids/plams_scripts.py
dragonfruit/mince/__init__.py
dragonfruit/mince/gui.py
dragonfruit/mince/process.py
dragonfruit/mince/utils.py
dragonfruit/slurm/__init__.py
dragonfruit/slurm/sbatch.py
dragonfruit/slurm/utils.py
dragonfruit/vasp/__init__.py
dragonfruit/vasp/base.py
dragonfruit/vasp/project.py
dragonfruit/vasp/simple_workflows.py
dragonfruit/vasp/vasp_default_errors.py
dragonfruit/vasp/vasp_errors.py
dragonfruit/vasp/vasp_parsers.py
dragonfruit/vasp/vasp_utils.py
dragonfruit/vasp/workflows/__init__.py
dragonfruit/vasp/workflows/legacy.py
dragonfruit/vasp/workflows/utils.py
dragonfruit/vasp/workflows/workflows.py
examples/__init__.py
examples/maibat_worker.py
examples/client/__init__.py
examples/client/pyos_project.py
examples/client/run_task.py
examples/client/send_task.py
examples/client/simple_vasp_class.py
dragonfruit-0.0.1b0.dist-info/LICENSE.md
dragonfruit-0.0.1b0.dist-info/METADATA
dragonfruit-0.0.1b0.dist-info/WHEEL
dragonfruit-0.0.1b0.dist-info/entry_points.txt
dragonfruit-0.0.1b0.dist-info/top_level.txt
dragonfruit-0.0.1b0.dist-info/RECORD
